{
  "Tokyo": 139.6922,
  "Osaka": 135.5022,
  "Nagoya": 136.9,
  "Yokohama": 139.6381,
  "Fukuoka": 130.4,
  "Sapporo": 141.35,
  "Kawasaki": 130.8149,
  "Kobe": 135.1956,
  "Kyoto": 135.7683,
  "Saitama": 139.6456,
  "Hiroshima": 132.4519,
  "Sendai": 140.8694,
  "Chiba": 140.1064,
  "Setagaya": 139.6532,
  "Kitakyushu": 130.8833,
  "Sakai": 139.7949,
  "Niigata": 139.0364,
  "Hamamatsu": 137.7275,
  "Nerima": 139.6517,
  "Ota-ku": 139.716,
  "Kumamoto": 130.7078,
  "Sagamihara": 139.3667,
  "Okayama": 133.9167,
  "Edogawa": 139.8683,
  "Adachi": 139.8044,
  "Shizuoka": 138.3828,
  "Honcho": 140.6944,
  "Kawaguchi": 139.7241,
  "Itabashi": 139.7093,
  "Suginami-ku": 139.6364,
  "Kagoshima": 130.55,
  "Hachioji": 139.316,
  "Koto-ku": 139.8173,
  "Himeji": 134.6833,
  "Utsunomiya": 139.8826,
  "Matsuyama": 132.7667,
  "Matsudo": 139.9032,
  "Ichikawa": 134.7633,
  "Higashi-osaka": 135.6008,
  "Nishinomiya-hama": 135.3416,
  "Oita": 131.6067,
  "Kurashiki": 133.7667,
  "Katsushika-ku": 139.8472,
  "Kanazawa": 136.6564,
  "Fukuyama": 133.3667,
  "Amagasaki": 135.4,
  "Fujisawa": 139.4667,
  "Machida": 139.4386,
  "Kashiwa": 139.9758,
  "Shinagawa-ku": 139.7302,
  "Aomori": 140.7307,
  "Toyota": 137.1563,
  "Takamatsu": 134.05,
  "Toyama": 137.2137,
  "Toyonaka": 135.4667,
  "Nagasaki": 129.8736,
  "Hirakata": 135.65,
  "Gifu": 136.7608,
  "Miyazaki": 131.4167,
  "Minamisuita": 135.5169,
  "Yokosuka": 139.6667,
  "Okazaki": 137.1744,
  "Ichinomiya": 140.3667,
  "Takasaki": 139.0033,
  "Toyohashi": 137.3915,
  "Kita-ku": 139.7336,
  "Shinjuku": 139.7034,
  "Nagano": 138.1947,
  "Nakano": 138.3694,
  "Kawagoe": 136.6667,
  "Wakayama": 135.1667,
  "Nara": 135.805,
  "Koshigaya": 139.7909,
  "Takatsuki": 135.6167,
  "Tokorozawa": 139.4686,
  "Otsu": 135.85,
  "Iwaki": 140.8877,
  "Hirosaki": 140.4638,
  "Maebashi": 139.0634,
  "Asahikawa": 142.365,
  "Koriyama": 140.3597,
  "Kochi": 133.5314,
  "Naha": 127.6792,
  "Toshima": 139.7167,
  "Yokkaichi": 136.6244,
  "Kasugai": 136.9722,
  "Meguro": 139.6983,
  "Oakashicho": 135.0,
  "Kurume": 130.5167,
  "Akita": 140.1026,
  "Sumida": 139.8015,
  "Morioka": 141.1545,
  "Ibaraki": 140.4245,
  "Fukushima": 140.4747,
  "Minato": 139.7515,
  "Tsu": 136.5057,
  "Fuchu": 132.5045,
  "Mito": 140.4712,
  "Ichihara": 140.1154,
  "Yao": 135.601,
  "Nagaoka": 135.7,
  "Kakogawacho-honmachi": 134.8333,
  "Fukui": 136.2196,
  "Hiratsuka": 139.35,
  "Soka": 139.8053,
  "Bunkyo-ku": 139.7523,
  "Tokushima": 134.5549,
  "Shinozaki": 130.9333,
  "Hakodate": 140.7289,
  "Chofugaoka": 139.5407,
  "Shibuya-ku": 139.6977,
  "Chigasaki": 139.4,
  "Yato": 139.45,
  "Yamagata": 136.7811,
  "Tsukuba-kenkyugakuen-toshi": 140.0764,
  "Fuji": 138.6763,
  "Sasebo": 129.715,
  "Arakawa": 139.7834,
  "Matsumoto": 137.972,
  "Neya": 135.6333,
  "Saga": 130.3,
  "Kasukabe": 139.7523,
  "Ageoshimo": 139.5932,
  "Taito": 139.78,
  "Takarazuka": 135.3406,
  "Atsugicho": 139.3667,
  "Ota": 139.3754,
  "Hachinohe": 141.4884,
  "Nishitokyo": 139.5383,
  "Kure": 132.5667,
  "Isesaki": 139.1968,
  "Kodaira": 139.4774,
  "Itami": 135.4,
  "Kamirenjaku": 139.5595,
  "Nagareyama": 139.9029,
  "Yachiyo": 139.8911,
  "Matsue": 133.0519,
  "Higashi-Hiroshima": 132.7333,
  "Hino": 136.246,
  "Suzuka": 136.5842,
  "Kumagaya": 139.3886,
  "Yamaguchi": 131.4667,
  "Anjomachi": 137.0803,
  "Odawara": 139.15,
  "Kishiwada": 135.3667,
  "Numazu": 138.8634,
  "Tachikawa": 139.4197,
  "Kofu": 138.5682,
  "Tottori": 134.2333,
  "Joetsu": 138.2361,
  "Toyokawa": 137.3759,
  "Chuo-ku": 139.772,
  "Narashino": 140.0265,
  "Uji": 135.7997,
  "Urayasu": 139.9022,
  "Kamakurayama": 139.5525,
  "Hitachi": 140.6515,
  "Izumo": 132.7667,
  "Niiza": 139.5653,
  "Sakura": 139.9664,
  "Tomakomai": 141.6055,
  "Nishio": 137.0667,
  "Oyama": 138.9873,
  "Iwata": 137.8515,
  "Takaoka": 137.0257,
  "Obihiro": 143.2,
  "Hadano": 139.2167,
  "Kushiro": 144.4661,
  "Ube": 131.25,
  "Musashino": 139.5661,
  "Miyakonojo": 131.0667,
  "Higashimurayama": 139.4685,
  "Ogaki": 136.6129,
  "Matsuzaka": 136.5276,
  "Daiwanishi": 135.4167,
  "Kariya": 134.3931,
  "Hitachi-Naka": 140.5347,
  "Tama": 133.9486,
  "Tochigi": 139.7303,
  "Noda": 139.8667,
  "Ueda": 138.2491,
  "Moriguchi": 135.5642,
  "Kawashiri": 135.4173,
  "Kukichuo": 139.6668,
  "Asaka": 139.5939,
  "Sayama": 139.4122,
  "Komaki": 136.9121,
  "Toda": 139.6779,
  "Imabari": 133.0,
  "Iruma": 139.3911,
  "Yonago": 133.3333,
  "Misato": 140.5821,
  "Kusatsu": 135.9667,
  "Kakamigahara": 136.8484,
  "Okinawa": 127.8056,
  "Ashikaga": 139.4497,
  "Fukayacho": 139.2815,
  "Fujita": 138.2577,
  "Kokubunji": 139.4622,
  "Ebina": 139.3908,
  "Kuwana": 136.6833,
  "Mino": 136.9076,
  "Koga": 130.4667,
  "Ishizaki": 141.3027,
  "Tsuchiura": 140.2,
  "Koganei": 139.503,
  "Zama": 139.4,
  "Shunan": 131.8,
  "Minoo": 135.4667,
  "Kisarazu": 139.9168,
  "Yaizu": 138.3247,
  "Inazawa": 136.7969,
  "Isahaya": 130.0667,
  "Ome": 139.2758,
  "Abiko": 140.0333,
  "Narita": 140.3183,
  "Onomichi": 133.2,
  "Iwakuni": 132.2189,
  "Seto": 137.0842,
  "Kadoma": 135.5833,
  "Omiyacho": 138.6216,
  "Osaki": 140.9556,
  "Iizuka": 130.6833,
  "Daitocho": 135.6167,
  "Matsubara": 135.55,
  "Kirishima": 130.7631,
  "Uruma": 127.8575,
  "Ise": 136.7167,
  "Honmachi": 144.6708,
  "Kashiwara": 135.6333,
  "Urasoe": 127.7219,
  "Tsuruoka": 139.8267,
  "Ebetsu": 141.5362,
  "Fujimino": 139.5198,
  "Handa": 136.9381,
  "Kasuga": 130.4667,
  "Ikoma": 135.7,
  "Akishima": 139.3535,
  "Konosu": 139.5222,
  "Aizuwakamatsu": 139.9298,
  "Nobeoka": 131.6667,
  "Fujimi": 138.2407,
  "Beppu": 131.5,
  "Shibuya": 139.7092,
  "Karatsu": 129.9667,
  "Nasushiobara": 140.0461,
  "Tokai": 140.5661,
  "Koencho": 143.8944,
  "Niihama": 133.2833,
  "Sano": 139.5783,
  "Hatsukaichi": 132.3333,
  "Kamagaya": 140.0008,
  "Kakegawa": 137.9984,
  "Nagahama": 136.2833,
  "Hofu": 131.5667,
  "Hikone": 136.2667,
  "Otaru": 140.9944,
  "Higashiomi": 136.2,
  "Oshu": 141.1391,
  "Habikino": 135.6,
  "Ichinoseki": 141.1266,
  "Tondabayashicho": 135.6,
  "Kazo": 139.6018,
  "Omuta": 130.45,
  "Shirayamamachi": 136.5656,
  "Marugame": 133.8,
  "Sandacho": 135.2333,
  "Mineshita": 138.9186,
  "Ikeda": 137.8746,
  "Tajimi": 137.1316,
  "Komatsu": 136.4455,
  "Kiryu": 139.4973,
  "Toride": 140.0504,
  "Onojo": 130.4833,
  "Inzai": 140.15,
  "Chikushino": 130.5167,
  "Ginowan": 127.7783,
  "Saijo": 133.1833,
  "Isehara": 139.3,
  "Sakado": 139.403,
  "Kawachinagano": 135.5667,
  "Kanoya": 130.8519,
  "Konan": 133.7,
  "Ashiya": 130.6639,
  "Yashio": 139.8392,
  "Inagi": 139.5046,
  "Komae": 139.5787,
  "Yotsukaido": 140.1679,
  "Nisshin": 137.0394,
  "Obu": 136.9637,
  "Settsu": 135.5622,
  "Wako": 139.6057,
  "Ama": 136.7832,
  "Kitanagoya": 136.8659,
  "Higashiyamato": 139.4265,
  "Warabi": 139.6797,
  "Takasagocho-takasemachi": 134.7833,
  "Ayase": 139.4333,
  "Owariasahi": 137.0354,
  "Kunitachi": 139.4414,
  "Shinkai": 139.5803,
  "Kiyose": 139.5265,
  "Kashiba": 135.7,
  "Izumiotsu": 135.4,
  "Katano": 135.6833,
  "Okegawa": 139.5427,
  "Joyo": 135.78,
  "Chiryu": 137.0506,
  "Musashimurayama": 139.3874,
  "Kiyosu": 136.8529,
  "Dazaifu": 130.5167,
  "Hekinan": 136.9934,
  "Yoshikawa": 139.8414,
  "Tsurugashima": 139.3931,
  "Yawata-shimizui": 135.7,
  "Chiyoda-ku": 139.7536,
  "Toyoake": 137.0128,
  "Hatogaya-honcho": 139.7412,
  "Fujiidera": 135.6,
  "Kitamoto": 139.5302,
  "Tomigusuku": 127.6689,
  "Nagakute": 137.0487,
  "Tagajo": 141.0043,
  "Yamatotakada": 135.7333,
  "Hasuda": 139.6624,
  "Osakasayama": 135.55,
  "Mukocho": 135.7,
  "Tsushima": 129.2833,
  "Fussa": 139.3333,
  "Koja": 127.8057,
  "Nonoichi": 136.6098,
  "Takaishi": 135.45,
  "Zushi": 139.5833,
  "Hamura": 139.3109,
  "Shijonawate": 135.6394,
  "Shiogama": 141.022,
  "Shiraoka": 139.6769,
  "Iwakura": 136.8714,
  "Takahama": 135.551,
  "Suzukawa": 139.3839,
  "Kasuya": 130.4806,
  "Inuma": 139.6242,
  "Togo": 137.0525,
  "Kumatori": 135.3558,
  "Katsuren-haebaru": 127.7285,
  "Oizumi": 139.4049,
  "Nakama": 130.7083,
  "Miyoshidai": 139.5265,
  "Kanie": 136.7868,
  "Oharu": 136.8201,
  "Harima": 134.8667,
  "Aizumi": 134.4951,
  "Fuso": 136.9132,
  "Nishihara": 127.7589,
  "Minamishiro": 139.7227,
  "Koryo": 135.75,
  "Kaita": 132.536,
  "Ninomiya": 139.2555,
  "Mizumaki": 130.695,
  "Chatan": 127.7639,
  "Ginan": 136.7825,
  "Oji": 135.7066,
  "Sanga": 135.6955,
  "Kitajima": 134.547,
  "Kasamatsucho": 136.7632,
  "Kanmaki": 135.7167,
  "Yonabaru": 127.7548,
  "Showa": 138.5351,
  "Kitagata": 136.6844,
  "Utazu": 133.8256,
  "Tadaoka-higashi": 135.4014,
  "Kawai": 135.7367,
  "Oyamazaki": 135.6885,
  "Toyoyama": 136.9121,
  "Izumisano": 135.3333,
  "Kani": 137.0613,
  "Chikusei": 139.9831,
  "Tsuyama": 134.0044,
  "Sakata": 139.8364,
  "Itoshima": 130.1978,
  "Saku": 138.4769,
  "Chitose": 141.6509,
  "Munakata": 130.5333,
  "Iida": 137.8214,
  "Omura": 129.9583,
  "Kamisu": 140.6645,
  "Shimada": 138.1927,
  "Kanuma": 139.7451,
  "Shibata": 140.7658,
  "Azumino": 137.9058,
  "Sanjo": 138.9617,
  "Higashi-Matsuyama": 139.3999,
  "Hanamaki Onsen": 141.1169,
  "Kitakami": 141.1132,
  "Satsumasendai": 130.3,
  "Imizucho": 137.0756,
  "Mihara": 133.0833,
  "Koka": 136.1667,
  "Fukuroi": 137.9247,
  "Mobara": 140.2881,
  "Gotenba": 138.9346,
  "Kameoka": 135.5667,
  "Kaizuka": 135.3667,
  "Iga": 136.1333,
  "Kitakoriyamacho": 135.7833,
  "Ushiku": 140.1496,
  "Sekimachi": 130.5438,
  "Chita": 136.8667,
  "Takayama": 137.2522,
  "Moriyama": 135.9942,
  "Yokotemachi": 140.5533,
  "Nakatsu": 131.1906,
  "Omihachiman": 136.0981,
  "Muroran": 140.974,
  "Shikokuchuo": 133.55,
  "Kimitsu": 139.9027,
  "Kashiwazaki": 138.559,
  "Yonezawa": 140.1168,
  "Gamagori": 137.2196,
  "Akiruno": 139.2941,
  "Echizen": 136.1298,
  "Natori-shi": 140.8918,
  "Gyoda": 139.4556,
  "Hanno": 139.3277,
  "Iwamizawa": 141.7759,
  "Mooka": 140.0134,
  "Maizuru": 135.3833,
  "Kizugawa": 135.8167,
  "Honjo": 139.1904,
  "Fukuchiyama": 135.1333,
  "Tsubame": 138.8822,
  "Toyooka": 134.8167,
  "Nikko": 139.6982,
  "Ryugasaki": 140.1823,
  "Aira": 130.6278,
  "Nabari": 136.1084,
  "Kai": 138.5158,
  "Toyomamachi-teraike": 141.1877,
  "Daisen": 133.5,
  "Tosu": 130.5,
  "Kyotanabe": 135.7667,
  "Nakatsugawa": 137.5006,
  "Sasagawa": 140.3727,
  "Tatebayashi": 139.5421,
  "Amakusa": 130.2,
  "Kandori": 140.0333,
  "Miki": 134.1344,
  "Tatsunocho-tominaga": 134.5453,
  "Yurihonjo": 140.0488,
  "Inuyama": 136.9445,
  "Kasama": 140.3043,
  "Shibukawa": 139.0633,
  "Otawara": 140.0156,
  "Ishioka": 140.2872,
  "Yukuhashi": 130.9833,
  "Katori": 140.4992,
  "Moriya": 139.9754,
  "Ritto": 136.0,
  "Eniwa": 141.5778,
  "Minami-Alps": 138.465,
  "Uwajima": 132.5667,
  "Anan": 134.6667,
  "Sabae": 136.1843,
  "Tanabe": 135.3833,
  "Soja": 133.7464,
  "Odate": 140.5642,
  "Fuefuki": 138.6397,
  "Kashima": 130.0989,
  "Hashima": 136.7033,
  "Yachimata": 140.3167,
  "Fukutsu": 130.4833,
  "Saiki": 131.9,
  "Shiojiri": 137.9534,
  "Ina": 137.954,
  "Ito": 139.1019,
  "Yanagawa": 130.4081,
  "Miyoshi": 133.8072,
  "Sodegaura": 139.9544,
  "Tamana": 130.5594,
  "Tenri": 135.8372,
  "Asahi": 137.5599,
  "Tsuruga": 136.0555,
  "Kurihara": 141.0215,
  "Shiroi": 140.0563,
  "Nago": 127.9775,
  "Kaga": 136.315,
  "Koshizuka": 130.7897,
  "Fujioka": 139.0746,
  "Tendo": 140.3779,
  "Itoman": 127.6658,
  "Ogoshi": 130.7833,
  "Mitoyo": 133.715,
  "Hita": 130.9333,
  "Aisai": 136.7282,
  "Tamba": 135.0333,
  "Sennan": 135.2761,
  "Hashimoto": 135.6,
  "Yame": 130.5589,
  "Shimotsuke": 139.8421,
  "Towada": 141.2059,
  "Sanyo-Onoda": 131.1833,
  "Joso": 139.9938,
  "Ogori": 130.55,
  "Kesennuma": 141.5699,
  "Hyuga": 131.6167,
  "Tahara": 137.2809,
  "Chikuma": 138.12,
  "Shirakawa": 140.2109,
  "Chichibu": 139.0855,
  "Kitahiroshima": 132.5384,
  "Tokoname": 136.8323,
  "Date": 140.8647,
  "Kokawa": 135.3653,
  "Ishikari": 141.3167,
  "Kosai": 137.5316,
  "Choshi": 140.8268,
  "Togane": 140.3661,
  "Mizuho": 139.354,
  "Minokamo": 137.0157,
  "Uki": 130.6864,
  "Kudamatsu": 131.8667,
  "Kan'onjicho": 133.6614,
  "Murakami": 139.48,
  "Nogata": 130.7322,
  "Takizawa": 141.0771,
  "Hidaka": 142.0743,
  "Toki": 137.1832,
  "Narutocho-mitsuishi": 134.6167,
  "Chino": 138.1588,
  "Funato": 135.3167,
  "Minamiuonuma": 138.8761,
  "Sakurai": 135.85,
  "Annaka": 138.8871,
  "Nihonmatsu": 140.4312,
  "Sado": 138.3683,
  "Hanyu": 139.5485,
  "Hamada": 132.0833,
  "Naka": 140.4868,
  "Mutsu": 141.1836,
  "Tomiya": 140.8833,
  "Imaricho-ko": 129.8833,
  "Usa": 131.3495,
  "Minami-Soma": 140.9573,
  "Miyakojima": 125.2811,
  "Izumi": 130.35,
  "Bando": 139.8887,
  "Tsukubamirai": 140.037,
  "Arao": 130.4353,
  "Satte": 139.7259,
  "Hannan": 135.2394,
  "Nanao": 136.9674,
  "Sakaidecho": 133.8667,
  "Yuki": 139.8766,
  "Kyotango": 135.0611,
  "Miyako": 141.9571,
  "Goshogawara": 140.4401,
  "Susono": 138.9068,
  "Nakagawa": 134.6622,
  "Higashiura": 136.9656,
  "Yasu": 136.0333,
  "Nichinan": 131.38,
  "Kameyama": 136.4517,
  "Chikugo": 130.5044,
  "Noshiromachi": 140.0266,
  "Tomisato": 140.5667,
  "Suzaka": 138.3073,
  "Tokamachi": 138.75,
  "Hikari": 131.9422,
  "Asakura": 130.6667,
  "Nomimachi": 136.5541,
  "Midori": 139.2811,
  "Yamaga": 130.6828,
  "Omitama": 140.3526,
  "Suwa": 138.114,
  "Ami": 140.2148,
  "Oamishirasato": 140.3167,
  "Sanmu": 140.4167,
  "Ishigaki": 124.1556,
  "Shimotsucho-kominami": 135.2167,
  "Ena": 137.4128,
  "Okaya": 138.0493,
  "Tonami": 136.9622,
  "Higashine": 140.3911,
  "Takeocho-takeo": 130.0215,
  "Ono": 136.6276,
  "Hitachi-ota": 140.5309,
  "Kikugawa": 138.0833,
  "Nanto": 136.9194,
  "Gosen": 139.1826,
  "Tomioka": 138.8899,
  "Noboribetsu": 141.1066,
  "Fujiyoshida": 138.8077,
  "Sanuki": 134.1794,
  "Hioki": 130.3731,
  "Shimeo": 130.4798,
  "Tamagawa": 130.8061,
  "Izunokuni": 138.9333,
  "Nakai": 133.6333,
  "Kurayoshi": 133.8167,
  "Kasaoka": 133.51,
  "Takashima": 136.0333,
  "Kikuchi": 130.8167,
  "Hokota": 140.5164,
  "Shima": 141.1555,
  "Hokuto": 138.4236,
  "Kitakata": 139.8748,
  "Numata": 139.0442,
  "Sugito": 139.7367,
  "Nanjo": 127.7706,
  "Tateyama": 137.3137,
  "Iwanuma": 140.8702,
  "Nagaizumi": 138.8972,
  "Taketoyo": 136.9147,
  "Kikuyo": 130.8287,
  "Masuda": 131.85,
  "Ogimachi": 130.2,
  "Hagi": 131.4,
  "Otofuke": 143.1981,
  "Goshikicho-aihara-minamidani": 134.7833,
  "Himi": 136.9731,
  "Yatomi": 136.7167,
  "Taniyama-chuo": 130.5176,
  "Shinshiro": 137.4986,
  "Makinohara": 138.2167,
  "Shimabara": 130.3697,
  "Kota": 137.1658,
  "Kobayashi": 130.9517,
  "Miura": 139.6167,
  "Awaji": 134.9167,
  "Obita": 129.8751,
  "Kasai": 134.8333,
  "Akaiwa": 134.0189,
  "Futtsu": 139.857,
  "Maniwa": 133.7525,
  "Minamishimabara": 130.3,
  "Shimotsuma": 139.9675,
  "Nanbei": 139.1,
  "Yuzawa": 140.4948,
  "Masaki": 132.7167,
  "Kitaibaraki": 140.751,
  "Komoro": 138.4258,
  "Sumoto": 134.9,
  "Unzen": 130.1875,
  "Amami": 129.4944,
  "Uozu": 137.4092,
  "Kato": 134.9667,
  "Yomitan": 127.7444,
  "Komono": 136.5075,
  "Agano": 139.226,
  "Aizawa": 139.3216,
  "Ozu": 130.8683,
  "Itoigawa": 137.8627,
  "Kasumigaura": 140.2371,
  "Sagae": 140.276,
  "Kurobeshin": 137.45,
  "Mibu": 139.8147,
  "Takikawa": 141.9104,
  "Mitsuke": 138.9127,
  "Tamba-Sasayama": 135.2219,
  "Higashimatsushima": 141.2104,
  "Inashiki": 140.3239,
  "Yoshinogawa": 134.3614,
  "Umi": 130.5111,
  "Hitachiomiya": 140.4109,
  "Omagari": 140.4754,
  "Sakuragawa": 140.0906,
  "Ibusuki": 130.6331,
  "Gujo": 136.9643,
  "Nishiwaki": 134.9722,
  "Misawa": 141.3691,
  "Ibara": 133.4667,
  "Katsuragi": 135.7333,
  "Maibara": 136.2833,
  "Tamamura": 139.1149,
  "Seika": 135.7833,
  "Kannan": 138.9534,
  "Tsubata": 136.7288,
  "Fuchucho": 133.2419,
  "Soma": 140.9196,
  "Mizunami": 137.2545,
  "Komatsushimacho": 134.5844,
  "Kanada": 130.9805,
  "Yasugicho": 133.2536,
  "Uto": 130.6669,
  "Morohongo": 139.316,
  "Rifu": 140.9759,
  "Miyajima": 130.4667,
  "Setouchi": 134.1,
  "Atami": 139.0716,
  "Usuki": 131.8,
  "Isumi": 140.3852,
  "Minami-Boso": 139.84,
  "Ofunato": 141.7086,
  "Kahoku": 140.3143,
  "Kamata": 130.7118,
  "Unnan": 132.9,
  "Tamura": 140.5667,
  "Iyo": 132.7,
  "Seiyo": 132.5108,
  "Sosa": 140.5642,
  "Shingu": 136.0,
  "Awa": 134.2964,
  "Abashiri": 144.2667,
  "Goto": 128.8333,
  "Inabe": 136.5614,
  "Shinjo": 140.3,
  "Toon": 132.8667,
  "Shiso": 134.55,
  "Uonuma": 138.9615,
  "Ojiya": 138.7951,
  "Sakaiminato": 133.2333,
  "Osawa": 130.3833,
  "Taishi": 135.6476,
  "Shobara": 133.0192,
  "Hayama": 139.5861,
  "Watari": 140.8676,
  "Minamikyushu": 130.4419,
  "Asakuchi": 133.5875,
  "Shimotoba": 135.663,
  "Kamaishi": 141.8857,
  "Bungoono": 131.5833,
  "Mashiki": 130.817,
  "Wakabadai": 141.6731,
  "Yamanashi": 138.6869,
  "So": 131.0194,
  "Oiso": 139.3113,
  "Kuji": 141.7757,
  "Yufu": 131.4333,
  "Kaizu": 136.6365,
  "Motosu": 136.6786,
  "Shiroishi": 130.1434,
  "Yorii": 139.193,
  "Minamisatsuma": 130.3228,
  "Shimanto": 133.1369,
  "Tawaramoto": 135.795,
  "Zentsujicho": 133.7833,
  "Namerikawa": 137.3412,
  "Shimizucho": 138.9029,
  "Nagato": 131.1833,
  "Bizen": 134.1889,
  "Odacho-oda": 132.5,
  "Yaese": 127.7186,
  "Chuo": 138.6339,
  "Namegata": 140.489,
  "Komagane": 137.9339,
  "Sasaguri": 130.5262,
  "Katagami": 139.9886,
  "Kuroishi": 140.6113,
  "Maebara": 140.0989,
  "Ayabe": 135.2667,
  "Yawatahama-shi": 132.4167,
  "Okagaki": 130.6111,
  "Hitoyoshi": 130.75,
  "Kaminokawa": 139.9099,
  "Yaita": 139.9241,
  "Nantan": 135.4667,
  "Omaezaki": 138.1281,
  "Kamisato": 139.1447,
  "Inami": 134.9135,
  "Kanzakimachi-kanzaki": 130.3667,
  "Tsuruno": 140.3801,
  "Yanai": 132.1167,
  "Yunoshima": 137.2441,
  "Motomiya": 140.3938,
  "Nanyo": 140.1476,
  "Hirakawacho": 140.5665,
  "Togitsu": 129.8486,
  "Tsuru": 138.9054,
  "Myoko": 138.2535,
  "Matsubushi": 139.8152,
  "Sue": 130.5072,
  "Yoshida": 138.252,
  "Chikuzen": 130.5952,
  "Inagawa": 135.3761,
  "Kitaakita": 140.3708,
  "Takanezawa": 139.9865,
  "Tomi": 138.3304,
  "Shibushi": 131.05,
  "Agui": 136.9153,
  "Kaminoyama": 140.2679,
  "Ikaruga": 135.7306,
  "Koshu": 138.7294,
  "Nirasaki": 138.4461,
  "Hanawa": 140.7884,
  "Hirado": 129.55,
  "Takahashi": 133.6164,
  "Asago": 134.85,
  "Ogawa": 139.2618,
  "Oyabe": 136.8687,
  "Saito": 131.4,
  "Aioi": 134.4667,
  "Izu": 138.9468,
  "Higashikagawa": 134.3667,
  "Taiwa": 140.8864,
  "Hiji": 131.5324,
  "Obama": 135.7466,
  "Mima": 134.1667,
  "Tainai": 139.4103,
  "Yahaba": 141.1429,
  "Kakuda": 140.7821,
  "Hikawa": 132.8432,
  "Ouda-yamaguchi": 135.9667,
  "Uchinada": 136.645,
  "Kitsuki": 131.6167,
  "Itako": 140.5554,
  "Ukiha": 130.75,
  "Gojo": 135.6964,
  "Niimi": 133.4731,
  "Takahagi": 140.7167,
  "Awara": 136.229,
  "Ichikikushikino": 130.2667,
  "Akitakata": 132.7064,
  "Nayoro": 142.4632,
  "Tarui": 136.5379,
  "Yoro": 136.5614,
  "Miyanaga": 130.6667,
  "Otake": 132.2167,
  "Toin": 136.5836,
  "Makubetsu": 143.3561,
  "Ora": 139.4623,
  "Arida": 135.1333,
  "Kami": 140.8548,
  "Saikaicho-kobago": 129.65,
  "Oguchi": 136.9078,
  "Nagai": 140.0405,
  "Tosa": 133.4333,
  "Omachi": 137.8511,
  "Miyaki": 130.4546,
  "Kunisakimachi-tsurugawa": 131.7311,
  "Ureshinomachi-shimojuku": 130.0667,
  "Nogi": 139.7407,
  "Ishii": 134.4406,
  "Mimata": 131.125,
  "Fujikawaguchiko": 138.7549,
  "Mimasaka": 134.1486,
  "Aridagawa": 135.2162,
  "Tono": 141.5334,
  "Minowa": 137.9819,
  "Ninohe": 141.3048,
  "Kamo": 139.0402,
  "Iki": 129.6914,
  "Nemuro": 145.5829,
  "Aso": 131.1239,
  "Oga": 139.8476,
  "Oirase": 141.3977,
  "Gose": 135.7333,
  "Nasukarasuyama": 140.1514,
  "Buzen": 131.1333,
  "Senboku": 140.7315,
  "Ogawara": 140.7308,
  "Isa": 130.6131,
  "Kamiamakusa": 130.4167,
  "Yugawara": 139.1083,
  "Wajimazakimachi": 136.8992,
  "Nyuzen": 137.5021,
  "Takehara": 132.9167,
  "Hachimantai": 141.0711,
  "Tadotsu": 133.7586,
  "Nasu": 140.121,
  "Kumano": 136.1002,
  "Nakagusuku": 127.7914,
  "Yoshioka": 139.0097,
  "Minamata": 130.4,
  "Mine": 131.2083,
  "Gobo": 135.15,
  "Nakashunbetsu": 144.9714,
  "Nikaho": 139.9077,
  "Meiwa": 139.5342,
  "Ayagawa": 133.923,
  "Mihama": 136.9082,
  "Gotsucho": 132.2167,
  "Uenohara": 139.1113,
  "Furukawa": 137.1862,
  "Yokoshibahikari": 140.5048,
  "Otsuki": 138.94,
  "Takahata": 140.1891,
  "Murayama": 140.3833,
  "Bungotakada": 131.45,
  "Shinhidaka": 142.3686,
  "Fukuyoshi": 130.78,
  "Yabu": 134.7667,
  "Mashiko": 140.0934,
  "Etajima": 132.45,
  "Aisho": 136.2123,
  "Matsuura": 129.7167,
  "Shisui": 140.2695,
  "Mobetsu": 143.3544,
  "Furano": 142.3832,
  "Ino": 133.4278,
  "Shimogamo": 138.9453,
  "Nishigo": 140.1554,
  "Ryuyo": 137.8167,
  "Bibai": 141.8538,
  "Susaki": 133.2931,
  "Namegawa": 139.361,
  "Sakae": 140.2439,
  "Tobe": 132.7922,
  "Takanabe": 131.5033,
  "Rumoi": 141.637,
  "Hirokawa": 130.5515,
  "Hakui": 136.779,
  "Satsuma": 130.4556,
  "Fukagawa": 142.0536,
  "Makurazaki": 130.2969,
  "Shirahama": 135.3481,
  "Shonai": 139.9047,
  "Yosano": 135.1529,
  "Kitatajima": 139.4816,
  "Karuizawa": 138.597,
  "Taketa": 131.4,
  "Fukusaki": 134.7603,
  "Ibigawa": 136.5686,
  "Godo": 136.6085,
  "Onga": 130.6683,
  "Kamiichi": 137.3624,
  "Iiyama": 138.3655,
  "Mukaiengaru": 143.5276,
  "Taka": 134.9234,
  "Ainan": 132.5833,
  "Mure": 134.1397,
  "Sukumo": 132.7167,
  "Arita": 129.849,
  "Akune": 130.2167,
  "Aizumisato": 139.8342,
  "Shichigahama": 141.0591,
  "Eiheiji": 136.2987,
  "Shimomura": 138.0802,
  "Motomachi": 144.1074,
  "Heguri": 135.7006,
  "Miyatoko": 130.9202,
  "Tatsuno": 137.9876,
  "Yoshimi": 139.4538,
  "Kunitomi": 131.3235,
  "Ranzan": 139.3205,
  "Toyono": 135.4941,
  "Kitanakagusuku": 127.7931,
  "Taku": 130.1167,
  "Yoichi": 140.7835,
  "Memuro-minami": 143.0508,
  "Shika": 136.778,
  "Kishi": 139.1232,
  "Oi": 139.1565,
  "Kiyama": 130.5232,
  "Rikuzen-Takata": 141.6254,
  "Minamishibetsucho": 142.4001,
  "Shirosato": 140.3762,
  "Arai": 137.5667,
  "Mitake": 137.1307,
  "Hinode": 139.2574,
  "Toba": 136.8434,
  "Ebino": 130.8167,
  "Shin-Kamigoto": 129.0733,
  "Miharu": 140.4932,
  "Kadogawa": 131.6461,
  "Mori": 140.5764,
  "Manno": 133.8414,
  "Minakami": 138.9991,
  "Minamichita": 136.9298,
  "Tsuiki": 131.0562,
  "Yabuki": 140.3386,
  "Kumage": 131.969,
  "Oyodo": 135.7897,
  "Katsuura": 140.3167,
  "Kushima": 131.2467,
  "Shintomi": 131.488,
  "Sunagawa": 141.9035,
  "Yoshinogari": 130.3989,
  "Shiraoi": 141.3559,
  "Miyazu": 135.2,
  "Mifune": 130.8019,
  "Nakanoto": 136.9015,
  "Nanbu": 133.3267,
  "Tohoku": 141.2579,
  "Oarai": 140.5749,
  "Kumiyama": 135.7328,
  "Kotoura": 133.7,
  "Yurihama": 133.8646,
  "Owase": 136.191,
  "Aki": 133.9,
  "Minamiminowa": 137.9751,
  "Kanan": 135.6296,
  "Nagasu": 130.4528,
  "Tachiarai": 130.6224,
  "Tsukumiura": 131.8667,
  "Gonohe": 141.308,
  "Miyota": 138.5068,
  "Matsushige": 134.5803,
  "Kasumi": 134.6333,
  "Yazu": 134.2505,
  "Yakumo": 140.2652,
  "Ashikita": 130.4932,
  "Kasagi": 135.5037,
  "Tobetsu": 141.517,
  "Tone": 140.1392,
  "Shizukuishi": 140.9758,
  "Sayo": 134.3558,
  "Daigo": 140.3552,
  "Tamaki": 136.6308,
  "Kanegasaki": 141.1163,
  "Wakuya": 141.1282,
  "Noto": 137.1477,
  "Kurate": 130.6742,
  "Kawaminami": 131.5259,
  "Kamitonda": 135.4288,
  "Kujukuri": 140.4333,
  "Uchiko": 132.6583,
  "Nakanojomachi": 138.841,
  "Kutchan": 140.7589,
  "Anpachi": 136.6654,
  "Aizubange": 139.8216,
  "Haga": 140.0582,
  "Mitane": 140.005,
  "Sera": 133.0566,
  "Misaki": 133.9582,
  "Fujisaki": 140.5028,
  "Betsukai": 145.1175,
  "Hirono": 141.7187,
  "Tabuse": 132.0414,
  "Obanazawa": 140.4,
  "Kushimoto": 135.7833,
  "Nishinoomote": 130.9967,
  "Suo-Oshima": 132.1952,
  "Shinto": 138.9671,
  "Ichikawamisato": 138.5024,
  "Oki": 130.4398,
  "Hasami": 129.8955,
  "Miho": 140.3019,
  "Asagiri": 130.8979,
  "Kihoku": 136.3372,
  "Yamada": 141.9489,
  "Itakura": 139.6019,
  "Furukawamen": 129.6504,
  "Tsukawaki": 131.1515,
  "Ishikawa": 140.4468,
  "Taki": 136.5462,
  "Kawaii": 140.0458,
  "Shichinohe": 141.1579,
  "Hokuei": 133.7667,
  "Hayashima": 133.8283,
  "Sakaki": 138.1801,
  "Minamiaizu": 139.7732,
  "Seiro": 139.2742,
  "Kadena": 127.7553,
  "Kakunodatemachi": 140.562,
  "Kisanuki": 130.9452,
  "Chosei": 140.35,
  "Fujikawa": 138.4613,
  "Nachikatsuura": 135.9411,
  "Tako": 140.4677,
  "Wakasa": 135.9082,
  "Kamigori": 134.3561,
  "Higashimiyoshi": 133.9369,
  "Hatoyama": 139.3341,
  "Yamanobe": 140.2622,
  "Shodoshima": 134.3089,
  "Chiran": 130.4416,
  "Tarumizu": 130.7594,
  "Kawatana": 129.8613,
  "Okinoshima": 133.3218,
  "Ugo": 140.4129,
  "Keisen": 130.6781,
  "Wake": 134.1575,
  "Itano": 134.4626,
  "Inawashiro": 140.1048,
  "Saka": 132.5136,
  "Matsushima": 141.0673,
  "Tonosho": 134.1884,
  "Yakage": 133.5872,
  "Kamikawa": 134.7397,
  "Tanagura": 140.3796,
  "Hashikami": 141.6211,
  "Motobu": 127.8978,
  "Shin'onsen": 134.4489,
  "Yamato": 130.9859,
  "Itayanagi": 140.4572,
  "Yuza": 139.9088,
  "Takamori": 137.8739,
  "Suzu": 137.2605,
  "Ashibetsu": 142.1896,
  "Kanra": 138.9218,
  "Kyotamba": 135.4194,
  "Shirataka": 140.0986,
  "Kasaishi": 140.3434,
  "Kawamata": 140.5983,
  "Matsukawa": 137.9097,
  "Nobeji": 141.1287,
  "Tsuruta": 140.4284,
  "Higashiagatsuma": 138.8203,
  "Marumori": 140.7654,
  "Sakawa": 133.2866,
  "Osako": 131.0059,
  "Hirao": 132.0732,
  "Hodatsushimizu": 136.7976,
  "Iwanai": 140.5146,
  "Iwate": 141.2122,
  "Ryuo": 136.1245,
  "Urakawa": 142.7682,
  "Tosashimizu": 132.95,
  "Yamamoto": 140.8781,
  "Kagamino": 133.933,
  "Satosho": 133.5569,
  "Yakushima": 130.6515,
  "Kamiita": 134.4049,
  "Motegi": 140.1876,
  "Mitai": 131.3077,
  "Koori": 140.5207,
  "Minabe": 135.3206,
  "Okuizumo": 133.0023,
  "Muroto-misakicho": 134.1519,
  "Yuasa": 135.1903,
  "Tagami": 139.058,
  "Kin": 127.926,
  "Higashiizu": 139.0333,
  "Kuriyama": 141.7843,
  "Zao": 140.6587,
  "Ichikai": 140.1022,
  "Ichinohe": 141.2954,
  "Chiyoda": 139.4424,
  "Ogose": 139.2942,
  "Yamanouchi": 138.4127,
  "Hikawadai": 130.6737,
  "Shoo": 134.1162,
  "Miyato": 139.1814,
  "Onna": 127.85,
  "Obuse": 138.3121,
  "Hakone": 139.0247,
  "Minamiise": 136.7036,
  "Matsuda-soryo": 139.1394,
  "Minamisanriku": 141.4624,
  "Ogano": 139.0086,
  "Otsuchi": 141.8994,
  "Iwai": 134.3333,
  "Nakayama": 140.2831,
  "Tokigawa": 139.2968,
  "Shirako": 140.3742,
  "Murata": 140.7224,
  "Rokunohe": 141.3248,
  "Naganuma": 141.6951,
  "Hoki": 133.4073,
  "Kamifurano": 142.4672,
  "Kiho": 136.0,
  "Kibichuo": 133.6935,
  "Minobu": 138.4424,
  "Kiso": 137.7831,
  "Higashikagura": 142.4515,
  "Tokunoshima": 129.0187,
  "Minamiaso": 131.0333,
  "Iizuna": 138.2355,
  "Nishi": 130.8411,
  "Shioya": 139.8506,
  "Kushijima": 130.7573,
  "Kawara": 130.8473,
  "Yaotsu": 137.1416,
  "Rokkasho": 141.3744,
  "Iwashita": 130.8114,
  "Kuroshio": 133.0167,
  "Onan": 132.4378,
  "Sakuho": 138.4834,
  "Tsuno": 131.5597,
  "Kami-kawabe": 137.0707,
  "Hiranai": 140.9559,
  "Biei": 142.4669,
  "Nakao": 139.2188,
  "Akabira": 142.0442,
  "Yamakita": 139.0838,
  "Nakoushi": 127.9728,
  "Minano": 139.0988,
  "Shimizu": 142.8846,
  "Hirayama": 130.5001,
  "Fujisawacho-niinuma": 141.3493,
  "Nagaoki": 130.6057,
  "Iijima": 137.9198,
  "Taragi": 130.9357,
  "Soeda": 130.854,
  "Otaki": 140.2454,
  "Miyada": 137.9443,
  "Hakubacho": 137.8619,
  "Takaharu": 131.0079,
  "Iwaizumi": 141.7964,
  "Torihama": 135.9406
}